helloworld/__init__.py
helloworld/__main__.py
helloworld/helloworld.py
helloworldmarcjourne-0.0.1.dist-info/METADATA
helloworldmarcjourne-0.0.1.dist-info/WHEEL
helloworldmarcjourne-0.0.1.dist-info/top_level.txt
helloworldmarcjourne-0.0.1.dist-info/RECORD
